torch_scope/__init__.py
torch_scope/__main__.py
torch_scope/commands.py
torch_scope/file_manager.py
torch_scope/sheet_writer.py
torch_scope/wrapper.py
torch_scope-0.5.6.dist-info/METADATA
torch_scope-0.5.6.dist-info/RECORD
torch_scope-0.5.6.dist-info/WHEEL
torch_scope-0.5.6.dist-info/entry_points.txt
torch_scope-0.5.6.dist-info/top_level.txt
