Metadata-Version: 2.1
Name: torch-scope
Version: 0.5.6
Summary: A Toolkit for Training, Tracking and Saving PyTorch Models
Home-page: https://github.com/LiyuanLucasLiu/Torch-Scope
Author: Lucas Liu
Author-email: llychinalz@gmail.com
License: Apache License 2.0
Platform: UNKNOWN
Classifier: Development Status :: 2 - Pre-Alpha
Classifier: Intended Audience :: Developers
Classifier: Natural Language :: English
Classifier: Programming Language :: Python :: 2
Classifier: Programming Language :: Python :: 2.7
Classifier: Programming Language :: Python :: 3
Classifier: Programming Language :: Python :: 3.4
Classifier: Programming Language :: Python :: 3.5
Classifier: Programming Language :: Python :: 3.6
Requires-Dist: numpy
Requires-Dist: tensorboardX
Requires-Dist: gitpython
Requires-Dist: torch
Requires-Dist: gspread
Requires-Dist: PyOpenSSL
Requires-Dist: oauth2client
